README.txt
setup.py
django_serene.egg-info/PKG-INFO
django_serene.egg-info/SOURCES.txt
django_serene.egg-info/dependency_links.txt
django_serene.egg-info/requires.txt
django_serene.egg-info/top_level.txt
serene/__init__.py
serene/mixins.py
serene/models.py
serene/resources.py
serene/serializers.py
serene/views.py
serene/tests/__init__.py
serene/tests/datetimestub.py
serene/tests/models.py
serene/tests/resources.py
serene/tests/test_mixins.py
serene/tests/test_resources.py
serene/tests/test_serializers.py
serene/tests/test_views.py