Metadata-Version: 1.0
Name: django-serene
Version: 0.0.8
Summary: An enhanced djangorestframework. Serene is a RESTful framework with a touch of sirisanthana
Home-page: http://code.google.com/p/django-serene/
Author: The Sirisanthana Team
Author-email: vsirisanthana@gmail.com
License: GPL-3.0
Download-URL: http://pypi.python.org/pypi/django-serene
Keywords: RESTful django djangorestframework
Platform: UNKNOWN
Classifier: Development Status :: 3 - Alpha
Classifier: Intended Audience :: Developers
Classifier: Programming Language :: Python
Classifier: Topic :: Software Development :: Libraries :: Python Modules
Classifier: License :: OSI Approved :: GNU General Public License (GPL)
